clouddojo/__init__.py
clouddojo/__main__.py
clouddojo/ascii_art.py
clouddojo/base_scenario.py
clouddojo/cli.py
clouddojo/default_learning_paths.py
clouddojo/hints.py
clouddojo/k8s_base_scenario.py
clouddojo/learning_path_definitions.py
clouddojo/learning_paths.py
clouddojo/metadata_registry.py
clouddojo/progress.py
clouddojo/scenario_metadata.py
clouddojo/setup.py
clouddojo/storytelling.py
clouddojo/scenarios/__init__.py
clouddojo/scenarios/cron-job-broken/__init__.py
clouddojo/scenarios/file-permissions-broken/__init__.py
clouddojo/scenarios/k8s-network-isolation/__init__.py
clouddojo/scenarios/k8s-network-isolation/manifests/network-isolation.yaml
clouddojo/scenarios/k8s-pod-failures/__init__.py
clouddojo/scenarios/k8s-pod-failures/manifests/pod.yaml
clouddojo/scenarios/k8s-service-discovery/__init__.py
clouddojo/scenarios/k8s-service-discovery/manifests/service-discovery.yaml
clouddojo/scenarios/nginx-broken/Dockerfile
clouddojo/scenarios/nginx-broken/__init__.py
clouddojo/scenarios/nginx-broken/default.broken
clouddojo/scenarios/nginx-broken/default.working
clouddojo/scenarios/nginx-broken/index.html
clouddojo/scenarios/nginx-broken-config/Dockerfile
clouddojo/scenarios/nginx-broken-config/__init__.py
clouddojo/scenarios/nginx-broken-config/default.broken
clouddojo/scenarios/nginx-broken-config/default.working
clouddojo/scenarios/nginx-broken-config/nginx.conf.broken
clouddojo/scenarios/nginx-broken-config/nginx.conf.working
clouddojo/scenarios/process-zombie/__init__.py
clouddojo-0.1.0.dist-info/licenses/LICENSE
tests/__init__.py
tests/test_progress.py
tests/test_scenarios.py
clouddojo-0.1.0.dist-info/METADATA
clouddojo-0.1.0.dist-info/WHEEL
clouddojo-0.1.0.dist-info/entry_points.txt
clouddojo-0.1.0.dist-info/top_level.txt
clouddojo-0.1.0.dist-info/RECORD
