Metadata-Version: 2.4
Name: clouddojo
Version: 0.1.0
Summary: A gamified, narrative-driven troubleshooting platform for DevOps/SRE engineers
Home-page: https://github.com/datakaitech/clouddojo-cli
Author: CloudDojo Contributors
Author-email: datakaitechnologies@gmail.com
Project-URL: Bug Reports, https://github.com/datakaitech/clouddojo-cli/issues
Project-URL: Source, https://github.com/datakaitech/clouddojo-cli
Project-URL: Documentation, https://github.com/datakaitech/clouddojo-cli#readme
Keywords: devops sre troubleshooting learning gamification docker kubernetes
Classifier: Development Status :: 4 - Beta
Classifier: Intended Audience :: Developers
Classifier: Intended Audience :: System Administrators
Classifier: Topic :: System :: Systems Administration
Classifier: Topic :: Education
Classifier: Topic :: Software Development :: Testing
Classifier: License :: OSI Approved :: MIT License
Classifier: Programming Language :: Python :: 3
Classifier: Programming Language :: Python :: 3.8
Classifier: Programming Language :: Python :: 3.9
Classifier: Programming Language :: Python :: 3.10
Classifier: Programming Language :: Python :: 3.11
Classifier: Operating System :: OS Independent
Requires-Python: >=3.8
License-File: LICENSE
Requires-Dist: click>=8.0.0
Requires-Dist: rich>=12.0.0
Requires-Dist: docker>=6.0.0
Provides-Extra: dev
Requires-Dist: pytest>=7.0.0; extra == "dev"
Requires-Dist: pytest-cov>=4.0.0; extra == "dev"
Requires-Dist: flake8>=5.0.0; extra == "dev"
Requires-Dist: black>=22.0.0; extra == "dev"
Dynamic: author
Dynamic: author-email
Dynamic: classifier
Dynamic: description
Dynamic: description-content-type
Dynamic: home-page
Dynamic: keywords
Dynamic: license-file
Dynamic: project-url
Dynamic: provides-extra
Dynamic: requires-dist
Dynamic: requires-python
Dynamic: summary
